odoo/addons/web_listview_range_select/README.rst
odoo/addons/web_listview_range_select/__init__.py
odoo/addons/web_listview_range_select/__manifest__.py
odoo/addons/web_listview_range_select/i18n/web_listview_range_select.pot
odoo/addons/web_listview_range_select/static/description/icon.png
odoo/addons/web_listview_range_select/static/src/js/web_listview_range_select.js
odoo/addons/web_listview_range_select/templates/assets.xml
odoo11_addon_web_listview_range_select-11.0.1.0.2.dist-info/METADATA
odoo11_addon_web_listview_range_select-11.0.1.0.2.dist-info/WHEEL
odoo11_addon_web_listview_range_select-11.0.1.0.2.dist-info/top_level.txt
odoo11_addon_web_listview_range_select-11.0.1.0.2.dist-info/RECORD
